CHANGES
MANIFEST.in
README
setup.py
pyramid_autoroute/__init__.py
pyramid_autoroute.egg-info/PKG-INFO
pyramid_autoroute.egg-info/SOURCES.txt
pyramid_autoroute.egg-info/dependency_links.txt
pyramid_autoroute.egg-info/entry_points.txt
pyramid_autoroute.egg-info/not-zip-safe
pyramid_autoroute.egg-info/requires.txt
pyramid_autoroute.egg-info/top_level.txt