Metadata-Version: 1.1
Name: pyramid-autoroute
Version: 1.2.0
Summary: Pyramid addon to auto detects views
Home-page: http://docs.pylonsproject.org
Author: UNKNOWN
Author-email: UNKNOWN
License: BSD-derived (http://www.repoze.org/LICENSE.txt)
Keywords: web wsgi pylons pyramid
Platform: UNKNOWN
Classifier: Intended Audience :: Developers
Classifier: Programming Language :: Python
Classifier: Topic :: Internet :: WWW/HTTP
Classifier: Topic :: Internet :: WWW/HTTP :: WSGI
Classifier: Programming Language :: Python
Classifier: Programming Language :: Python :: 2
Classifier: Programming Language :: Python :: 2.7
Classifier: Programming Language :: Python :: 3
Classifier: Programming Language :: Python :: 3.6
Classifier: Programming Language :: Python :: 3.7
Classifier: Framework :: Pyramid
